ilovetim/__init__.py
ilovetim/ilovetim.py
ilovetim-0.1.5.dist-info/METADATA
ilovetim-0.1.5.dist-info/RECORD
ilovetim-0.1.5.dist-info/WHEEL
ilovetim-0.1.5.dist-info/entry_points.txt
ilovetim-0.1.5.dist-info/top_level.txt
