Metadata-Version: 2.1
Name: ilovetim
Version: 0.1.5
Summary: Download images from instagram
Home-page: https://github.com/xwaynec/ilovetimliao
Author: xwaynec
Author-email: xwaynec@gmail.com
License: v0.1.0, 2017.07.13 -- Initial release.
Requires-Dist: beautifulsoup4 (==4.6.0)
Requires-Dist: certifi (==2017.7.27.1)
Requires-Dist: chardet (==3.0.4)
Requires-Dist: idna (==2.5)
Requires-Dist: requests (==2.18.3)
Requires-Dist: urllib3 (==1.22)
